Workbook

Sheet precios damian
F1: lista precios | H1: dólar | I1: 1430
A3: DESCRIPCIoN | B3: MARCA | C3: MODELO | D3: PRECIO (USD) | E3: venta en dolares | F3: costo pesos | G3: precio venta PESOS
A4: cough asisst | D4: 6980 | E4: =D4*1.3+10 -> 9084 | G4: =E4*I1 -> 12990120
A5: AUTO CPAP CON HUMIDIFICADOR | B5: BMC | C5: G3 | D5: 518 | E5: =D5*1.3+10 -> 683.4 | F5: =D5*I1 -> 740740 | G5: =E5*I1 -> 977262
A6: BPAP CON HUMIDIFICADOR AVAPS | B6: BMC | C6: G2 | D6: 1.012,00 | E6: =D6*1.3+10 -> 1325.6 | F6: =D6*I1 -> 1447160 | G6: =E6*I1 -> 1895608
A7: bpap con humidificador Y FREC | B7: bmc | C7: g3 | D7: 690 | E7: =D7*1.3+10 -> 907 | G7: =E7*I1 -> 1297010
A8: CONCENTRADOR YUWELL Y BMC | B8: YUWELL | D8: 541 | E8: =D8*1.3+10 -> 713.3 | F8: =E8*1.3+10 -> 937.29 | G8: =E8*I1 -> 1020019
A9: AUTOCPAP CON HUMIDIFICADOR Y MODEM | B9: PHILIPS | C9: DREAMSTATION | D9: 575 | E9: =D9*1.3+10 -> 757.5 | G9: =E9*I1 -> 1083225
A10: TERMOHUMIDIFICADOR | B10: PHILIPS | C10: DREAMSTATION | D10: 144 | E10: =D10*1.3+10 -> 197.2 | G10: =E10*I1 -> 281996
A11: AUTO CPAP CON HUMIDIFICADOR | B11: BMC | C11: G2 | D11: 334 | E11: =D11*1.3+10 -> 444.2 | F11: =D11*I1 -> 477620 | G11: =E11*I1 -> 635206
A12: AUTO CPAP SIN HUMIDIFICADOR | B12: BMC | C12: G2 | D12: 230 | E12: =D12*1.3+10 -> 309 | F12: =D12*I1 -> 328900 | G12: =E12*I1 -> 441870
A13: AUTO CPAP CON HUMIDIFICADOR | B13: BMC | C13: G2S | D13: 311 | E13: =D13*1.3+10 -> 414.3 | F13: =D13*$I$1 -> 444730 | G13: =E13*I1 -> 592449 | H13: 1
A14: AUTO CPAP SIN HUMIDIFICADOR | B14: YUWELL | C14: YH-560 | D14: 402,50 | E14: =D14*1.3+10 -> 533.25 | F14: =D14*$I$1 -> 575575 | G14: =E14*I1 -> 762547.5
A15: AUTO CPAP CON HUMIDIFICADOR | B15: YUWELL | C15: YH-560 | D15: 460,00 | E15: =D15*1.3+10 -> 608 | F15: =D15*$I$1 -> 657800 | G15: =E15*I1 -> 869440 | H15: 1
A16: CPAP CON HUMIDIFICADOR | B16: BMC | C16: G2S | D16: 320,00 | E16: =D16*1.3+10 -> 426 | F16: =D16*$I$1 -> 457600 | G16: =E16*I1 -> 609180 | H16: 1
A17: CPAP CON HUMIDIFICADOR | B17: YAMIND | C17: DM26 | D17: 320,00 | E17: =D17*1.3+10 -> 426 | F17: =D17*$I$1 -> 457600 | G17: =E17*I1 -> 609180
A18: CPAP CON HUMIDIFICADOR | B18: YUWELL | C18: YH-350 | D18: 250 | E18: =D18*1.3+10 -> 335 | F18: =D18*$I$1 -> 357500 | G18: =E18*I1 -> 479050
A19: CPAP CON HUMIDIFICADOR | B19: YUWELL | C19: YH-360 | D19: 305 | E19: =D19*1.3+10 -> 406.5 | F19: =D19*$I$1 -> 436150 | G19: =E19*I1 -> 581295 | H19: 1
A20: CPAP PHILIPS CON MODEM | B20: DREASTATION | D20: 437 | E20: =D20*1.3+10 -> 578.1 | G20: =E20*I1 -> 826683
A21: ASPIRADOR DE SECRESIONES | B21: MOVIVAC | C21: A-550 | D21: 549 | E21: =D21*1.3+10 -> 723.7 | G21: =E21*I1 -> 1034891
A22: CPAP CON HUMIDIFICADOR RESMED MAS NUBE | B22: AIRSENSE | C22: 10 | D22: 466 | E22: =D22*1.3+10 -> 615.8 | F22: =D22*$I$1 -> 666380 | G22: =E22*I1 -> 880594
A23: AUTO CPAP CON HUMIDIFICADOR SIN NUBE RESMED | B23: AIRSENSE | C23: 10 | D23: 690,00 | E23: =D23*1.3+10 -> 907 | F23: =D23*$I$1 -> 986700 | G23: =E23*I1 -> 1297010
A24: AUTO CPAP CON HUMIDIFICADOR CON NUBE RESMED | B24: AIRSENSE | C24: 10 | D24: 633 | E24: =D24*1.3+10 -> 832.9 | F24: =D24*$I$1 -> 905190 | G24: =E24*I1 -> 1191047
A25: AUTOCPAP SIN HUMIDIFICADOR + NASAL N5AH BMC | B25: M1 | C25: MINI | D25: 1070.5 | E25: =D25*1.3+10 -> 1401.65 | F25: =E25*1.3+10 -> 1832.145 | G25: =E25*I1 -> 2004359.5
A26: AUTOCPAP SIN HUMIDIFICADOR + NASAL PILLOW P2H BMC | B26: M1 | C26: MINI | D26: 1070.5 | E26: 1401 | F26: =D26*$I$1 -> -433331470 | G26: =E26*I1 -> 2003430
A27: AUTOCPAP CON HUMIDIFICADOR | B27: PHILIPS | C27: DREAMSTATION | D27: 678,50 | E27: =D27*1.3+10 -> 892.05 | F27: =D27*$I$1 -> 970255 | G27: =E27*I1 -> 1275631.5
A28: BPAP CON HUMIDIFICADOR AVAPS | B28: YUWELL | C28: YH-830 | D28: 759,00 | E28: =D28*1.3+10 -> 996.7 | F28: =D28*$I$1 -> 1085370 | G28: =E28*I1 -> 1425281
A29: BPAP CON HUMIDIFICADOR ST + MASCARA NASAL F2 TALLE M | B29: BMC | C29: G3 | D29: 690 | E29: =D29*1.3+10 -> 907 | F29: =D29*$I$1 -> 986700 | G29: =E29*I1 -> 1297010
A30: CONCENTRADOR DE OXIGENO PORTATIL PHILIPS | B30: SIMPLY | C30: GO | D30: 2.990,00 | E30: =D30*1.3+10 -> 3897 | F30: =D30*$I$1 -> 4275700 | G30: =E30*I1 -> 5572710 | H30: 1
A31: concentrador portatil cont 2L 2 baterias | B31: gce | D31: 2300 | E31: =D31*1.3+10 -> 3000 | G31: =E31*I1 -> 4290000
A32: concentrador portatil cont 2L 2 baterias | B32: gce | D32: 2875 | E32: =D32*1.3+10 -> 3747.5 | G32: =E32*I1 -> 5358925
A33: NASAL S CON APOYA FRENTE | B33: YUWELL | C33: YN-02 | D33: 25,00 | E33: =D33*1.3+10 -> 42.5 | F33: =D33*$I$1 -> 35750 | G33: =E33*I1 -> 60775
A34: NASAL M CON APOYA FRENTE | B34: YUWELL | C34: YN-02 | D34: 25,00 | E34: =D34*1.3+10 -> 42.5 | F34: =D34*$I$1 -> 35750 | G34: =E34*I1 -> 60775
A35: NASAL L CON APOYA FRENTE | B35: YUWELL | C35: YN-02 | D35: 25,00 | E35: =D35*1.3+10 -> 42.5 | F35: =D35*$I$1 -> 35750 | G35: =E35*I1 -> 60775
A36: NASAL L M S SIN APOYA FRENTE | B36: YUWELL | C36: YN-03 | D36: 32 | E36: =D36*1.3+10 -> 51.6 | G36: =E36*I1 -> 73788
A37: BUCONASAL S | B37: YUWELL | C37: YF-01 | D37: 28,00 | E37: =D37*1.3+10 -> 46.4 | F37: =D37*$I$1 -> 40040 | G37: =E37*I1 -> 66352
A38: BUCONASAL M | B38: YUWELL | C38: YF-01 | D38: 28,00 | E38: =D38*1.3+10 -> 46.4 | F38: =D38*$I$1 -> 40040 | G38: =E38*I1 -> 66352
A39: BUCONASAL L | B39: YUWELL | C39: YF-01 | D39: 28,00 | E39: =D39*1.3+10 -> 46.4 | F39: =D39*$I$1 -> 40040 | G39: =E39*I1 -> 66352
A40: BUCONASAL S | B40: YUWELL | C40: YF-02 | D40: 32,00 | E40: =D40*1.3+10 -> 51.6 | F40: =D40*$I$1 -> 45760 | G40: =E40*I1 -> 73788
A41: BUCONASAL M | B41: YUWELL | C41: YF-02 | D41: 32,00 | E41: =D41*1.3+10 -> 51.6 | F41: =D41*$I$1 -> 45760 | G41: =E41*I1 -> 73788
A42: BUCONASAL L | B42: YUWELL | C42: YF-02 | D42: 32,00 | E42: =D42*1.3+10 -> 51.6 | F42: =D42*$I$1 -> 45760 | G42: =E42*I1 -> 73788
A43: PILLOW MULTITALLE | B43: YUWELL | C43: YP-01 | D43: 45 | E43: =D43*1.3+10 -> 68.5 | F43: =D43*$I$1 -> 64350 | G43: =E43*I1 -> 97955
A44: NASAL PILLOW M | B44: YUWELL | C44: YP-01 | D44: 24 | E44: =D44*1.3+10 -> 41.2 | F44: =D44*$I$1 -> 34320 | G44: =E44*I1 -> 58916
A45: NASAL PILLOW L | B45: YUWELL | C45: YP-01 | D45: 24 | E45: =D45*1.3+10 -> 41.2 | F45: =D45*$I$1 -> 34320 | G45: =E45*I1 -> 58916
A46: PILLOW MULTITALLE | B46: BMC | C46: P2 | D46: 61,00 | E46: =D46*1.3+10 -> 89.3 | F46: =D46*$I$1 -> 87230 | G46: =E46*I1 -> 127699
A47: nasal dreamwear | B47: PHILIPS | C47: DREAMWEAR | D47: 110 | E47: =D47*1.3+10 -> 153 | F47: =D47*$I$1 -> 157300 | G47: =E47*I1 -> 218790
A48: DREAMWEAR BUCO NASAL S | B48: PHILIPS | C48: DREAMWEAR | D48: 113 | E48: =D48*1.3+10 -> 156.9 | F48: =D48*$I$1 -> 161590 | G48: =E48*I1 -> 224367
A49: DREAMWEAR BUCO NASAL M | B49: PHILIPS | C49: DREAMWEAR | D49: 113 | E49: =D49*1.3+10 -> 156.9 | F49: =D49*$I$1 -> 161590 | G49: =E49*I1 -> 224367
A50: DREAMWEAR BUCO NASAL L | B50: PHILIPS | C50: DREAMWEAR | D50: 113 | E50: =D50*1.3+10 -> 156.9 | F50: =D50*$I$1 -> 161590 | G50: =E50*I1 -> 224367
A51: DREAMWEAR NASAL WISP PEDIATRICO | B51: PHILIPS | C51: DREAMWEAR | D51: 161,00 | E51: =D51*1.3+10 -> 219.3 | F51: =D51*$I$1 -> 230230 | G51: =E51*I1 -> 313599 | H51: 1
A52: MASCARA NASAL PICO TALLE | B52: L | C52: PHILIPS | D52: 52,00 | E52: =D52*1.3+10 -> 77.6 | F52: =D52*$I$1 -> 74360 | G52: =E52*I1 -> 110968
A53: NASAL S | B53: YUWELL | C53: YN-03 | D53: 31,05 | E53: =D53*1.3+10 -> 50.365 | F53: =D53*$I$1 -> 44401.5 | G53: =E53*I1 -> 72021.95
A54: NASAL M | B54: YUWELL | C54: YN-03 | D54: 31,05 | E54: =D54*1.3+10 -> 50.365 | F54: =D54*$I$1 -> 44401.5 | G54: =E54*I1 -> 72021.95
A55: NASAL L | B55: YUWELL | C55: YN-03 | D55: 31,05 | E55: =D55*1.3+10 -> 50.365 | F55: =D55*$I$1 -> 44401.5 | G55: =E55*I1 -> 72021.95
A56: BUCONASAL S | B56: BMC | C56: F2 | D56: 28 | E56: =D56*1.3+10 -> 46.4 | F56: =D56*$I$1 -> 40040 | G56: =E56*I1 -> 66352
A57: BUCONASAL M | B57: BMC | C57: F2 | D57: 28 | E57: =D57*1.3+10 -> 46.4 | F57: =D57*$I$1 -> 40040 | G57: =E57*I1 -> 66352
A58: BUCONASAL L | B58: BMC | C58: F2 | D58: 28 | E58: =D58*1.3+10 -> 46.4 | F58: =D58*$I$1 -> 40040 | G58: =F58*1.3 -> 52052
A59: BUCONASAL CON APOYA FRENTE S | B59: BMC | C59: N4 | D59: 31 | E59: =D59*1.3+10 -> 50.3 | G59: =E59*I1 -> 71929
A60: NASAL S | B60: BMC | C60: N2 | D60: 27,60 | E60: =D60*1.3+10 -> 45.88 | F60: =D60*$I$1 -> 39468 | G60: =F60*1.3 -> 51308.4
A61: NASAL M | B61: BMC | C61: N2 | D61: 27,60 | E61: =D61*1.3+10 -> 45.88 | F61: =D61*$I$1 -> 39468 | G61: =F61*1.3 -> 51308.4
A62: NASAL L | B62: BMC | C62: N2 | D62: 27,60 | E62: =D62*1.3+10 -> 45.88 | F62: =D62*$I$1 -> 39468 | G62: =F62*1.3 -> 51308.4
A63: NASAL S CON APOYA FRENTE | B63: BMC | C63: N5 | D63: 31,05 | E63: =D63*1.3+10 -> 50.365 | F63: =D63*$I$1 -> 44401.5 | G63: =F63*1.3 -> 57721.95
A64: NASAL M CON APOYA FRENTE | B64: BMC | C64: N5 | D64: 23.5 | E64: =D64*1.3+10 -> 40.55 | F64: =D64*$I$1 -> 33605 | G64: =F64*1.3 -> 43686.5
A65: nasal con apoya frente m y l | B65: bmc | C65: n4 | D65: 20 | E65: =D65*1.3+10 -> 36 | G65: =E65*I1 -> 51480
A66: TERMOHUMIDIFICADOR | B66: PHILIPS | C66: DREAMSTATION | D66: 143,75 | E66: =D66*1.3+10 -> 196.875 | F66: =D66*$I$1 -> 205562.5 | G66: =E66*I1 -> 281531.25
A67: TERMOHUMIDIFICADOR | B67: BMC | C67: G2 | D67: 103,50 | E67: =D67*1.3+10 -> 144.55 | F67: =D67*$I$1 -> 148005 | G67: =E67*I1 -> 206706.5
A68: CUBETA | B68: BMC | C68: G2 | D68: 51,75 | E68: =D68*1.3+10 -> 77.275 | F68: =D68*$I$1 -> 74002.5 | G68: =E68*I1 -> 110503.25
A69: 54 | B69: TUBULADURA | C69: RESMED | D69: 13.8 | E69: =D69*1.3+10 -> 27.94 | F69: =D69*$I$1 -> 19734 | G69: =E69*I1 -> 39954.2
A70: NASAL SIN APOYA FRENTE S | B70: BMC | C70: N5A | D70: 38 | E70: =D70*1.3+10 -> 59.4 | F70: =D70*$I$1 -> 54340 | G70: =E70*I1 -> 84942
A71: NASAL SIN APOYA FRENTE M | B71: BMC | C71: N5A | D71: 38 | E71: =D71*1.3+10 -> 59.4 | F71: =D71*$I$1 -> 54340 | G71: =E71*I1 -> 84942 | H71: 1
A72: NASAL SIN APOYA FRENTE L | B72: BMC | C72: N5A | D72: 38 | E72: =D72*1.3+10 -> 59.4 | F72: =D72*$I$1 -> 54340 | G72: =E72*I1 -> 84942
A73: NASAL SIN APOYA FRENTE XL | B73: BMC | C73: N5A | D73: 38 | E73: =D73*1.3+10 -> 59.4 | F73: =D73*$I$1 -> 54340 | G73: =E72*I1 -> 84942
A74: NASAL CON APOYA FRENTE S M L | B74: BMC | C74: N5 | D74: 24 | E74: =D74*1.3+10 -> 41.2 | F74: =D74*$I$1 -> 34320 | G74: =E74*I1 -> 58916
A75: BUCONASAL SIN APOYA FRENTE S | B75: BMC | C75: F5A | D75: 32 | E75: =D75*1.3+10 -> 51.6 | F75: =D75*$I$1 -> 45760 | G75: =E75*I1 -> 73788 | H75: 1
A76: BUCONASAL SIN APOYA FRENTE M | B76: BMC | C76: F5A | D76: 32 | E76: =D76*1.3+10 -> 51.6 | F76: =D76*$I$1 -> 45760 | G76: =E76*I1 -> 73788
A77: buconasal simil dreamwear | B77: bmc | C77: f6 | D77: 96 | E77: =D77*1.3+10 -> 134.8 | G77: =E77*I1 -> 192764
A78: BUCONASAL SIN APOYA FRENTE L | B78: BMC | C78: F5A | D78: 32 | E78: =D78*1.3+10 -> 51.6 | F78: =D78*$I$1 -> 45760 | G78: =E78*I1 -> 73788
A79: BUCONASAL GEL L | B79: PHILIPS | C79: AMARA | D79: 115,00 | E79: =D79*1.3+10 -> 159.5 | F79: =D79*$I$1 -> 164450 | G79: =E79*I1 -> 228085
A80: BUCONASAL M | B80: PHILIPS | C80: AMARA | D80: 108,10 | E80: =D80*1.3+10 -> 150.53 | F80: =D80*$I$1 -> 154583 | G80: =E80*I1 -> 215257.9
A81: NASAL SIN APOYA FRENTE S | B81: RESMED | C81: N20 | D81: 73,60 | E81: =D81*1.3+10 -> 105.68 | F81: =D81*$I$1 -> 105248 | G81: =E81*I1 -> 151122.4
A82: NASAL SIN APOYA FRENTE M | B82: RESMED | C82: N20 | D82: 73,60 | E82: =D82*1.3+10 -> 105.68 | F82: =D82*$I$1 -> 105248 | G82: =E82*I1 -> 151122.4
A83: NASAL SIN APOYA FRENTE L | B83: RESMED | C83: N20 | D83: 73,60 | E83: =D83*1.3+10 -> 105.68 | F83: =D83*$I$1 -> 105248 | G83: =E83*I1 -> 151122.4
A84: BUCONASAL SIN APOYA FRENTE S | B84: RESMED | C84: F20 | D84: 138,00 | E84: =D84*1.3+10 -> 189.4 | F84: =D84*$I$1 -> 197340 | G84: =E84*I1 -> 270842
A85: BUCONASAL SIN APOYA FRENTE M | B85: RESMED | C85: F20 | D85: 138,00 | E85: =D85*1.3+10 -> 189.4 | F85: =D85*$I$1 -> 197340 | G85: =E85*I1 -> 270842
A86: BUCONASAL SIN APOYA FRENTE L | B86: RESMED | C86: F20 | D86: 138,00 | E86: =D86*1.3+10 -> 189.4 | F86: =D86*$I$1 -> 197340 | G86: =E86*I1 -> 270842
A87: buconasal sin apoya frente
A88: BUCONASAL SIN APOYA FRENTE S | B88: RESMED | C88: F30 | D88: 150 | E88: =D88*1.3+10 -> 205 | F88: =D88*$I$1 -> 214500 | G88: =E88*I1 -> 293150
A89: BUCONASAL SIN APOYA FRENTE M | B89: RESMED | C89: F30 | D89: 150 | E89: =D89*1.3+10 -> 205 | F89: =D89*$I$1 -> 214500 | G89: =E89*I1 -> 293150
A90: BUCONASAL SIN APOYA FRENTE L | B90: RESMED | C90: F30 | D90: 150 | E90: =D90*1.3+10 -> 205 | F90: =D90*$I$1 -> 214500 | G90: =E90*I1 -> 293150 | H90: 1
A91: ALMOHADILLA NASAL | B91: RESMED | C91: AIRFIT | D91: 112,70 | E91: =D91*1.3+10 -> 156.51 | F91: =D91*$I$1 -> 161161 | G91: =E91*I1 -> 223809.3
A92: 75 MASCARA NASAL MIMIMO CONTACTO (talles sw/s/m) RESMED | B92: AIRFIT | C92: N30i | D92: 109.25 | E92: =D92*1.3+10 -> 152.025 | F92: =D92*$I$1 -> 156227.5 | G92: =E92*I1 -> 217395.75 | H92: 1
A93: MASCARA NASAL RESMED | B93: MIRAGE | C93: FX | D93: 65,55 | E93: =D93*1.3+10 -> 95.215 | F93: =D93*$I$1 -> 93736.5 | G93: =E93*I1 -> 136157.45
A94: NASAL CON APOYA FRENTE M | B94: RESCOMF | C94: NM2 | D94: 25 | E94: =D94*1.3 -> 32.5 | F94: =D94*$I$1 -> 35750 | G94: =E94*I1 -> 46475
A95: BUCONASAL CON APOYA FRENTE S | B95: BMC | C95: FM | D95: 34,50 | E95: =D95*1.3+10 -> 54.85 | F95: =D95*$I$1 -> 49335 | G95: =E95*I1 -> 78435.5
A96: BUCONASAL SIN APOYA FRENTE S | B96: BMC | C96: FM1A | D96: 34 | E96: =D96*1.3+10 -> 54.2 | F96: =D96*$I$1 -> 48620 | G96: =E96*I1 -> 77506
A97: BUCONASAL CON APOYA FRENTE M | B97: BMC | C97: F1B | D97: 29 | E97: =D97*1.3+10 -> 47.7 | F97: =D97*$I$1 -> 41470 | G97: =E97*I1 -> 68211
A98: BUCONASAL CON APOYA FRENTE S | B98: BMC | C98: NM4 | D98: 31,05 | E98: =D98*1.3+10 -> 50.365 | F98: =D98*$I$1 -> 44401.5 | G98: =E98*I1 -> 72021.95
A99: POLIGRAFO BMC | B99: YH-600B | C99: PRO | D99: 1.207,50 | E99: 1150 | F99: =D99*$I$1 -> 1726725 | G99: =E99*I1 -> 1644500
A100: POLIGRAFO (incluye 30 canulas) BMC | B100: YH-600B | C100: PRO | D100: 1.380,00 | E100: 1380 | F100: =D100*$I$1 -> 1973400 | G100: =E100*I1 -> 1973400
A101: CONCENTRADOR DE OXIGENO 5LT LONFIANG | B101: YUWELL | C101: 7F5 | D101: 540 | E101: =D101*1.3+10 -> 712 | F101: =D101*$I$1 -> 772200 | G101: =E101*I1 -> 1018160
...

Sheet precios mark
A1: Producto | B1: Precio (USD) | C1: IVA | E1: precio venta dolares | F1: VENTA EN PESOS | G1: VALOR DOLAR | H1: 1485
A2: concentrador portatil Kingon p2-e 1 litro 5 niveles | B2: 1650 | C2: 1.105 | D2: =B2*C2 -> 1823.25 | E2: =D2*1.3+10 -> 2380.225 | F2: =E2*H1 -> 3534634.1
A3: Concentrador portatil Kingon P2-S3. (1,8 kg.; 0,62 litros/min; 3 niveles pulsado) | B3: 1300 | C3: 1.105 | D3: =B3*C3 -> 1436.5 | E3: =D3*1.3+10 -> 1877.45 | F3: =E3*H1 -> 2788013.2
A4: concentrador portatil Kingon p2-e6 1,2 litro 6 niveles | B4: 1850 | C4: 1.105 | D4: =B4*C4 -> 2044.25 | E4: =D4*1.3+10 -> 2667.525 | F4: =E4*H1 -> 3961274.6
A5: concentrador portatil kingon p2-e7 1,4 litros 7 niveles | B5: 2150 | C5: 1.105 | D5: =B5*C5 -> 2375.75 | E5: =D5*1.3+10 -> 3098.475 | F5: =E5*H1 -> 4601235.4
A6: Concentrador portatil Kingon P2-TOC (8 kg.; carrito | B6: 2400 | C6: 1.105 | D6: =B6*C6 -> 2652 | E6: =D6*1.3+10 -> 3457.6 | F6: =E6*H1 -> 5134536
A7: BATERIA KINGON P2-tOC | B7: 550 | C7: 1.105 | D7: =B7*C7 -> 607.75 | E7: =D7*1.3+10 -> 800.075 | F7: =E7*H1 -> 1188111.4
A9: bateria kingon | B9: 290 | C9: 1.105 | D9: =B9*C9 -> 320.45 | E9: =D9*1.3+10 -> 426.585 | F9: =E9*H1 -> 633478.72
A10: mochila kingon | B10: 120 | C10: 1.21 | D10: =B10*C10 -> 145.2 | E10: =D10*1.3+10 -> 198.76 | F10: =E10*H1 -> 295158.6
A12: filtro kingon 5 unidades | B12: 16 | C12: =B12*1.21 -> 19.36 | D12: =B12*C12 -> 309.76 | E12: =D12*1.3+10 -> 412.688 | F12: =E12*H1 -> 612841.68
A13: CONCENTRADOR ESTACIONARIO MICITECH | B13: 520 | C13: 1.105 | D13: =B13*C13 -> 574.6 | E13: =D13*1.3+10 -> 756.98 | F13: =E13*H1 -> 1124115.3
A14: CPAP Topson | B14: 260 | C14: 1.105 | D14: =B14*C14 -> 287.3 | E14: =D14*1.3+10 -> 383.49 | F14: =E14*H1 -> 569482.65
A15: CPAP + Humidificador Topson | B15: 270 | C15: 1.105 | D15: =B15*C15 -> 298.35 | E15: =D15*1.3+10 -> 397.855 | F15: =E15*H1 -> 590814.68
A16: AUTOCPAP Topson | B16: 330 | C16: 1.105 | D16: =B16*C16 -> 364.65 | E16: =D16*1.3+10 -> 484.045 | F16: =E16*H1 -> 718806.82
A17: AUTOCPAP + Humidificador Topson | B17: 340 | C17: 1.105 | D17: =B17*C17 -> 375.7 | E17: =D17*1.3+10 -> 498.41 | F17: =E17*H1 -> 740138.85
A18: BPAP + Humidificador Topson | B18: 850 | C18: 1.105 | D18: =B18*C18 -> 939.25 | E18: =D18*1.3+10 -> 1231.025 | F18: =E18*H1 -> 1828072.1
A19: AUTOBPAP + Humidificador Topson | B19: 900 | C19: 1.105 | D19: =B19*C19 -> 994.5 | E19: =D19*1.3+10 -> 1302.85 | F19: =E19*H1 -> 1934732.2
A20: BPAP con Frecuencia + Humidificador Topson | B20: 950 | C20: 1.105 | D20: =B20*C20 -> 1049.75 | E20: =D20*1.3+10 -> 1374.675 | F20: =E20*H1 -> 2041392.4
A21: BPAP AVAPS 25 + Humidificador Topson | B21: 1000 | C21: 1.105 | D21: =B21*C21 -> 1105 | E21: =D21*1.3+10 -> 1446.5 | F21: =E21*H1 -> 2148052.5
A22: BPAP AVAPS 30 + Humidificador Topson | B22: 1200 | C22: 1.105 | D22: =B22*C22 -> 1326 | E22: =D22*1.3+10 -> 1733.8 | F22: =E22*H1 -> 2574693
A23: BPAP AVAPS 35 + Humidificador Topson | B23: 1300 | C23: 1.105 | D23: =B23*C23 -> 1436.5 | E23: =D23*1.3+10 -> 1877.45 | F23: =E23*H1 -> 2788013.2
A24: Humidificador Topson (incluye carcasa reusable) | B24: 50 | C24: 1.21 | D24: =B24*C24 -> 60.5 | E24: =D24*1.3+10 -> 88.65 | F24: =E24*H1 -> 131645.25
A25: Carcasa reusable para humidificador | B25: 30 | C25: 1.21 | D25: =B25*C25 -> 36.3 | E25: =D25*1.3+10 -> 57.19 | F25: =E25*H1 -> 84927.15
A26: Tubladura 22 mm premium Topson | B26: 14 | C26: 1.21 | D26: =B26*C26 -> 16.94 | E26: =D26*1.3 -> 22.022 | F26: =E26*H1 -> 32702.67
A27: Tubladura 15 mm premium Topson | B27: 18 | C27: 1.21 | D27: =B27*C27 -> 21.78 | E27: =D27*1.3 -> 28.314 | F27: =E27*H1 -> 42046.29
A28: Filtro exterior Topson | B28: 2.8 | C28: 1.21 | D28: =B28*C28 -> 3.388 | E28: =D28*1.3+10 -> 14.4044 | F28: =E28*H1 -> 21390.534
A29: HSINER 821 (S, M, L) | B29: 27 | C29: 1.21 | D29: =B29*C29 -> 32.67 | E29: =D29*1.3+10 -> 52.471 | F29: =E29*H1 -> 77919.435
A30: HSINER 825 (S, M, L) | B30: 27 | C30: 1.21 | D30: =B30*C30 -> 32.67 | E30: =D30*1.3+10 -> 52.471 | F30: =E30*H1 -> 77919.435
A31: HSINER Comfo plus (S, M, L) | B31: 33 | C31: 1.21 | D31: =B31*C31 -> 39.93 | E31: =D31*1.3+10 -> 61.909 | F31: =E31*H1 -> 91934.865
A32: HSINER 843 (S, M, L) | B32: 36 | C32: 1.21 | D32: =B32*C32 -> 43.56 | E32: =D32*1.3+10 -> 66.628 | F32: =E32*H1 -> 98942.58
A33: YUWELL YN-02 (S, M, L) | B33: 27 | C33: 1.21 | D33: =B33*C33 -> 32.67 | E33: =D33*1.3+10 -> 52.471 | F33: =E33*H1 -> 77919.435
A34: YUWELL YN-03 (S, M, L) | B34: 36 | C34: 1.21 | D34: =B34*C34 -> 43.56 | E34: =D34*1.3+10 -> 66.628 | F34: =E34*H1 -> 98942.58
A35: HSINER 101 (4 talles incluidos) | B35: 60 | C35: 1.21 | D35: =B35*C35 -> 72.6 | E35: =D35*1.3+10 -> 104.38 | F35: =E35*H1 -> 155004.3
A36: YUWELL YP-01 (3 talles incluidos) | B36: 60 | C36: 1.21 | D36: =B36*C36 -> 72.6 | E36: =D36*1.3+10 -> 104.38 | F36: =E36*H1 -> 155004.3
A37: HSINER 825 (S, M, L) | B37: 36 | C37: 1.21 | D37: =B37*C37 -> 43.56 | E37: =D37*1.3+10 -> 66.628 | F37: =E37*H1 -> 98942.58
A38: HSINER Comfo (S, M, L) | B38: 36 | C38: 1.21 | D38: =B38*C38 -> 43.56 | E38: =D38*1.3+10 -> 66.628 | F38: =E38*H1 -> 98942.58
A39: YUWELL YF-01 (S, M, L) | B39: 36 | C39: 1.21 | D39: =B39*C39 -> 43.56 | E39: =D39*1.3+10 -> 66.628 | F39: =E39*H1 -> 98942.58
A40: YUWELL YF-02 (S, M, L) | B40: 40 | C40: 1.21 | D40: =B40*C40 -> 48.4 | E40: =D40*1.3+10 -> 72.92 | F40: =E40*H1 -> 108286.2
A41: Nasal HSINER Cirri Mini (S, M, L, XS) | B41: 60 | C41: 1.21 | D41: =B41*C41 -> 72.6 | E41: =D41*1.3+10 -> 104.38 | F41: =E41*H1 -> 155004.3 | G41: 1
B42: 70 | C42: 1.21 | D42: =B42*C42 -> 84.7 | E42: =D42*1.3+10 -> 120.11 | F42: =E42*H1 -> 178363.35
A43: NeoQ Infant nasal (XS, S, M, L) | B43: 85 | C43: 1.21 | D43: =B43*C43 -> 102.85 | E43: =D43*1.3+10 -> 143.705 | F43: =E43*H1 -> 213401.92 | G43: 1
A44: Infant CPAP Kit (00, 0, 1, 2, 3, 4, 5) | B44: 55 | C44: 1.21 | D44: =B44*C44 -> 66.55 | E44: =D44*1.3+10 -> 96.515 | F44: =E44*H1 -> 143324.77

Sheet stock mascaras
A1: Marca | B1: Modelo | C1: Talle | D1: Stock | E1: precio
B2: NASALES
A3: RESCOM M | B3: NASAL CON APOYA | C3: M | D3: 2 | E3: ='precios damian'!G94 -> 46475
A4: RESCOM | C4: L | D4: 1
A5: DRAGER | D5: 1
A6: DREAMWEAR | B6: NASAL | D6: 1 | E6: ='precios damian'!G47 -> 218790
A7: BMC | B7: N2 NASAL CON APOYA | C7: M | D7: 1 | E7: ='precios damian'!G61 -> 51308.4
A8: BMC | B8: N4 NASAL CON APOYA | C8: S | D8: 1 | E8: ='precios damian'!G59 -> 71929
A9: BMC | B9: N5 NASAL CON APOYA | C9: L | D9: 1 | E9: ='precios damian'!G63 -> 57721.95
A10: BMC | B10: N5A NASAL SIN APOYA | C10: M | D10: 2 | E10: ='precios damian'!G72 -> 84942
A11: BMC | B11: N5A NASAL SIN APOYA | C11: L | D11: 1 | E11: ='precios damian'!G73 -> 84942
A12: YUWELL | B12: YN 03 NASAL SIN APOYA | C12: S | D12: 0 | E12: ='precios damian'!G25 -> 2004359.5
A13: HSINER | B13: NASAL CON APOYA CHILD | C13: L | D13: 0
A14: HSINER | B14: NASAL CON APOYA | C14: M | D14: 0
A15: HSINER | B15: NASAL CHILD | C15: M | D15: 0 | E15: ='precios mark'!F41 -> 155004.3
A16: DRAGUERS | B16: NASAL CON APOYA | C16: M | D16: 0 | E16: ='precios damian'!G107 -> 65608.4
A17: YUWELL | B17: YN 02 NASAL CON APOYA | C17: M | D17: 4 | E17: ='precios damian'!G33 -> 60775
A18: YUWELL | B18: YN 03 NASAL SIN APOYA | C18: S | D18: 1 | E18: ='precios damian'!G36 -> 73788
B20: FACIALES | D20: 0
A21: HSINER | B21: FACIAL CON APOYA | C21: M | D21: 0
A22: HSINER FACIAL CON APOYA M 2 | C22: M | D22: 0
A23: HSINER | B23: FACIAL CON APOYA | C23: M | D23: 0
A24: YUWELL | B24: YF 02 FULLFACE SIN APOYA | C24: L | D24: 1 | E24: ='precios damian'!G40 -> 73788
A25: YUWELL | B25: YF 02 FULLFACE SIN APOYA | C25: S | D25: 0 | E25: ='precios damian'!G41 -> 73788
A26: YEWELL | B26: YF 02 FULLFACE SIN APOYA | C26: M | D26: 1 | E26: =E25 -> 73788
A27: BMC | B27: F5A FULL FACE SIN APOYA | C27: S | D27: 1 | E27: ='precios damian'!G76 -> 73788
A28: BMC | B28: F2 FULL FACE CON APOYA | C28: M | D28: 2 | E28: ='precios damian'!G56 -> 66352
A29: bmc | B29: f6 simil dreamwear | C29: s,m,l | D29: 1 | E29: ='precios damian'!G77 -> 192764
A30: DREAMWEAR | B30: nasobucal L | D30: 1 | E30: ='precios damian'!G48 -> 224367
D31: 0
